md2_hash/__init__.py
md2_hash/md2.py
md2hash-1.0.2.dist-info/licenses/LICENSE
md2hash-1.0.2.dist-info/METADATA
md2hash-1.0.2.dist-info/WHEEL
md2hash-1.0.2.dist-info/top_level.txt
md2hash-1.0.2.dist-info/RECORD
